[
    {
        "0": "松",
        "1": "柏"
    },
    {
        "0": "缕",
        "1": "麻"
    },
    {
        "0": "蚁阵",
        "1": "蜂衙"
    },
    {
        "0": "頳鳞",
        "1": "白鹭"
    },
    {
        "0": "冻雀",
        "1": "昏鸦"
    },
    {
        "0": "白堕酒",
        "1": "碧沉茶"
    },
    {
        "0": "品笛",
        "1": "吹笳"
    },
    {
        "0": "秋凉梧堕叶",
        "1": "春暖杏开花"
    },
    {
        "0": "雨长苔痕侵壁砌",
        "1": "月移梅影上窗纱"
    },
    {
        "0": "飒飒秋风，度城头之筚篥",
        "1": "迟迟晚照，动江上之琵琶"
    },
    {
        "0": "优",
        "1": "劣"
    },
    {
        "0": "凸",
        "1": "凹"
    },
    {
        "0": "翠竹",
        "1": "黄花"
    },
    {
        "0": "松杉",
        "1": "杞梓"
    },
    {
        "0": "菽麦",
        "1": "桑麻"
    },
    {
        "0": "山不断",
        "1": "水无涯"
    },
    {
        "0": "煮酒",
        "1": "烹茶"
    },
    {
        "0": "鱼游池面水",
        "1": "鹭立岸头沙"
    },
    {
        "0": "百亩风翻陶令秫",
        "1": "一畦雨熟邵平瓜"
    },
    {
        "0": "闲捧竹根，饮李白一壶之酒",
        "1": "偶擎桐叶，啜卢仝七碗之茶"
    },
    {
        "0": "吴",
        "1": "楚"
    },
    {
        "0": "蜀",
        "1": "巴"
    },
    {
        "0": "落日",
        "1": "流霞"
    },
    {
        "0": "酒钱",
        "1": "诗债"
    },
    {
        "0": "柏叶",
        "1": "松花"
    },
    {
        "0": "驰驿骑",
        "1": "泛仙槎"
    },
    {
        "0": "碧玉",
        "1": "丹砂"
    },
    {
        "0": "设桥偏送笋",
        "1": "开道竟还瓜"
    },
    {
        "0": "楚国大夫沉汨水",
        "1": "洛阳才子谪长沙"
    },
    {
        "0": "书箧琴囊，乃士流活计",
        "1": "药炉茶鼎，实闲客生涯"
    }
]