[
    {
        "0": "兴",
        "1": "废"
    },
    {
        "0": "附",
        "1": "攀"
    },
    {
        "0": "露草",
        "1": "霜菅"
    },
    {
        "0": "歌廉",
        "1": "借寇"
    },
    {
        "0": "习孔",
        "1": "希颜"
    },
    {
        "0": "山垒垒",
        "1": "水潺潺"
    },
    {
        "0": "奉璧",
        "1": "探镮"
    },
    {
        "0": "礼由公旦作",
        "1": "诗本仲尼删"
    },
    {
        "0": "驴困客方经灞水",
        "1": "鸡鸣人已出函关"
    },
    {
        "0": "几夜霜飞，已有苍鸿辞北塞",
        "1": "数朝雾暗，岂无玄豹隐南山"
    },
    {
        "0": "犹",
        "1": "尚"
    },
    {
        "0": "侈",
        "1": "悭"
    },
    {
        "0": "雾髻",
        "1": "烟鬟"
    },
    {
        "0": "莺啼",
        "1": "鹊噪"
    },
    {
        "0": "独鹤",
        "1": "双鹇"
    },
    {
        "0": "黄牛峡",
        "1": "金马山"
    },
    {
        "0": "结草",
        "1": "衔环"
    },
    {
        "0": "昆山惟玉集",
        "1": "合浦有珠还"
    },
    {
        "0": "阮籍旧能为眼白",
        "1": "老莱新爱着衣斑"
    },
    {
        "0": "栖迟避世人，草衣木食",
        "1": "窈窕倾城女，云鬓花颜"
    },
    {
        "0": "姚",
        "1": "宋"
    },
    {
        "0": "柳",
        "1": "颜"
    },
    {
        "0": "赏善",
        "1": "惩奸"
    },
    {
        "0": "愁中",
        "1": "梦里"
    },
    {
        "0": "巧慧",
        "1": "痴顽"
    },
    {
        "0": "孔北海",
        "1": "谢东山"
    },
    {
        "0": "使越",
        "1": "征蛮"
    },
    {
        "0": "淫声闻濮上",
        "1": "离曲听阳关"
    },
    {
        "0": "骁将袍披仁贵白",
        "1": "小儿衣着老莱斑"
    },
    {
        "0": "茅舍无人，难却尘埃生榻上",
        "1": "竹亭有客，尚留风月在窗间"
    }
]